{
  "timestamp": "2025-12-16T05:23:29.155704-05:00",
  "platform": "Linux-6.16.8+kali-amd64-x86_64-with-glibc2.41",
  "uname": {
    "sysname": "Linux",
    "node": "dragonfly",
    "release": "6.16.8+kali-amd64",
    "version": "#1 SMP PREEMPT_DYNAMIC Kali 6.16.8-1kali1 (2025-09-24)",
    "machine": "x86_64"
  },
  "cpu_count_logical": 4,
  "cpu_count_physical": 2,
  "cpu_freq_mhz": {
    "current": 1290.243,
    "min": 400.0,
    "max": 3400.0
  },
  "percpu_percent": [
    16.3,
    18.1,
    13.7,
    18.6
  ],
  "loadavg": [
    1.4521484375,
    1.1513671875,
    0.71044921875
  ],
  "mem": {
    "total": 16531931136,
    "available": 11467436032,
    "percent": 30.6,
    "used": 5064495104
  },
  "swap": {
    "total": 499118080,
    "used": 1011712,
    "percent": 0.2
  },
  "disk": {
    "total": 97825230848,
    "used": 18370039808,
    "free": 74438594560,
    "percent": 18
  },
  "top_cpu": [
    {
      "cpu_percent": 0.0,
      "pid": 1,
      "memory_percent": 0.09912995563061121,
      "username": "root",
      "name": "systemd"
    },
    {
      "cpu_percent": 0.0,
      "pid": 2,
      "memory_percent": 0.0,
      "username": "root",
      "name": "kthreadd"
    },
    {
      "cpu_percent": 0.0,
      "pid": 3,
      "memory_percent": 0.0,
      "username": "root",
      "name": "pool_workqueue_release"
    },
    {
      "cpu_percent": 0.0,
      "pid": 4,
      "memory_percent": 0.0,
      "username": "root",
      "name": "kworker/R-rcu_gp"
    },
    {
      "cpu_percent": 0.0,
      "pid": 5,
      "memory_percent": 0.0,
      "username": "root",
      "name": "kworker/R-sync_wq"
    },
    {
      "cpu_percent": 0.0,
      "pid": 6,
      "memory_percent": 0.0,
      "username": "root",
      "name": "kworker/R-kvfree_rcu_reclaim"
    }
  ],
  "top_mem": [
    {
      "cpu_percent": 0.0,
      "pid": 981,
      "memory_percent": 5.927951525674683,
      "username": "root",
      "name": "Xorg"
    },
    {
      "cpu_percent": 0.0,
      "pid": 38492,
      "memory_percent": 4.6199613688010945,
      "username": "adam",
      "name": "code"
    },
    {
      "cpu_percent": 0.0,
      "pid": 32319,
      "memory_percent": 4.197030015985665,
      "username": "adam",
      "name": "code"
    },
    {
      "cpu_percent": 0.0,
      "pid": 105930,
      "memory_percent": 3.327877593210899,
      "username": "adam",
      "name": "code"
    },
    {
      "cpu_percent": 0.0,
      "pid": 1339,
      "memory_percent": 1.3810306740440563,
      "username": "adam",
      "name": "xfce4-panel"
    },
    {
      "cpu_percent": 0.0,
      "pid": 32234,
      "memory_percent": 1.3704511961499621,
      "username": "adam",
      "name": "code"
    }
  ]
}